{
  "format_version": "1.20.0",
  "minecraft:entity": {
    "description": {
      "identifier": "mine_structure:unicorn_gift_box",
      "is_spawnable": true,
      "is_summonable": true,
      "is_experimental": false
    },
    "components": {
      "minecraft:type_family": {
        "family": [
          "mine_structure_furniture",
          "unicorn_gift_box"
        ]
      },
      "minecraft:collision_box": {
        "width": 0.8,
        "height": 0.9
      },
      "minecraft:health": {
        "value": 12,
        "max": 12
      },
      "minecraft:physics": {
        "has_gravity": false,
        "has_collision": true
      },
      "minecraft:pushable": {
        "is_pushable": false,
        "is_pushable_by_piston": false
      },
      "minecraft:interact": {
        "interactions": [
          {
            "interact_text": "action.interact.open",
            "swing": true,
            "play_sounds": "random.orb",
            "on_interact": {
              "event": "mine_structure:open_gift",
              "target": "self"
            }
          }
        ]
      }
    },
    "events": {
      "mine_structure:open_gift": {
        "queue_command": {
          "target": "self",
          "command": "playanimation @s animation.unicorn_gift_box.lid_open"
        }
      }
    }
  }
}